{
  "products": [
    {
      "url": "https://www.tokopedia.com/putra-siregar-store/spesial-putra-siregar-iphone-17-pro-new-launching-new-produk-garansi-resmi-indonesia-1733343861743978301",
      "name": "SPESIAL PUTRA SIREGAR | IPHONE 17 PRO NEW LAUNCHING NEW PRODUK GARANSI RESMI INDONESIA - COSMIC ORANGE, 256",
      "price": "Rp26.500.000",
      "store_name": "Putra siregar store_NEW",
      "rating": null,
      "review_count": null,
      "scraped_at": "2026-03-10T00:32:53.527750"
    },
    {
      "url": "https://www.tokopedia.com/tradem/apple-iphone-17-pro-original-1733512360637203461",
      "name": null,
      "price": null,
      "store_name": null,
      "rating": null,
      "review_count": null,
      "scraped_at": "2026-03-10T00:33:31.162406"
    },
    {
      "url": "https://www.tokopedia.com/kungfu-gadget/kg-apple-iphone-17-pro-series-garansi-resmi-ibox-gdn-1733195417491047609",
      "name": "(KG) Apple iPhone 17 Pro Series Garansi Resmi IBOX / GDN - Iphone 17 Pro 256GB, Deep Blue",
      "price": "Rp23.326.000",
      "store_name": "Kungfu Gadget",
      "rating": 5.0,
      "review_count": 11,
      "scraped_at": "2026-03-10T00:33:41.695689"
    },
    {
      "url": "https://www.tokopedia.com/royalltech/apple-iphone-17-pro-1tb-all-collors-resmi-apple-indonesia-segel-greenpeel-1733546747226129911",
      "name": "APPLE iPhone 17 PRO 1TB All Collors Resmi APPLE INDONESIA Segel Greenpeel - COSMIC ORANGE, 256GB",
      "price": "Rp23.499.000",
      "store_name": "royalltech",
      "rating": 5.0,
      "review_count": 22,
      "scraped_at": "2026-03-10T00:34:06.495125"
    },
    {
      "url": "https://www.tokopedia.com/agresponsel/iphone-17-pro-256gb-kamera-48mp-baterai-3998-mah-garansi-resmi-indonesia-1733361538893842199",
      "name": "iPhone 17 PRO 256GB Kamera 48MP & Baterai 3998 mAh Garansi Resmi Indonesia - DEEP BLUE",
      "price": "Rp23.198.000",
      "store_name": null,
      "rating": 5.0,
      "review_count": 1,
      "scraped_at": "2026-03-10T00:34:32.658228"
    },
    {
      "url": "https://www.tokopedia.com/ljsofficial/iphone-17-pro-256-gb-512-gb-1tb-garansi-resmi-indonesia-1732870514079991198",
      "name": "Iphone 17 Pro 256 GB 512 GB 1TB Garansi Resmi Indonesia - Blue, 256GB",
      "price": "Rp22.379.712",
      "store_name": "LJS Phone",
      "rating": 5.0,
      "review_count": 13,
      "scraped_at": "2026-03-10T00:34:54.159249"
    },
    {
      "url": "https://www.tokopedia.com/topsellofficial/iphon-17-pro-256gb-512gb-1tb-new-original-garansi-resmi-indonesia-1-tahun-1732814659663922545",
      "name": "İPhon 17 Pro 256GB | 512GB | 1TB New Original Garansi Resmi Indonesia 1 Tahun - Cosmic Orange, 256GB",
      "price": "Rp24.119.000",
      "store_name": "TOPSELL OFFICIAL",
      "rating": 5.0,
      "review_count": 1,
      "scraped_at": "2026-03-10T00:35:18.532315"
    },
    {
      "url": "https://www.tokopedia.com/dmzstoreofficial/iphone-17-pro-256-gb-cosmic-orange-like-new-garansi-resmi-1733490936703780825",
      "name": "IPhone 17 Pro 256 Gb Cosmic Orange Like New Garansi Resmi",
      "price": "Rp22.500.000",
      "store_name": "DMZ Store Official",
      "rating": null,
      "review_count": null,
      "scraped_at": "2026-03-10T00:35:31.483058"
    },
    {
      "url": "https://www.tokopedia.com/4gcell45/new-iphone-17-pro-256gb-garansi-resmi-ibox-1733489510024644021",
      "name": null,
      "price": null,
      "store_name": null,
      "rating": null,
      "review_count": null,
      "scraped_at": "2026-03-10T00:36:01.415058"
    },
    {
      "url": "https://www.tokopedia.com/r-shop-cahaya/iphone-17-pro-256gb-512gb-1tb-garansi-resmi-indonesia-ibox-paa-ida-saa-new-segel-original-garansi-1-tahun-1733155221240776623",
      "name": "Iphone 17 PRO 256GB/512GB/1TB Garansi (RESMI) Indonesia IBOX PAA IDA SAA NEW SEGEL ORIGINAL Garansi 1 Tahun - biru, 512GB",
      "price": "Rp30.923.000",
      "store_name": "R Shop Cahaya",
      "rating": 5.0,
      "review_count": 4,
      "scraped_at": "2026-03-10T00:36:12.281403"
    },
    {
      "url": "https://www.tokopedia.com/ayrivshop/apple-iphone-17-pro-1tb-512gb-256gb-a19-pro-chip-silver-cosmic-orange-deep-blue-resmi-256gb-deep-blue-1733589700784915631",
      "name": null,
      "price": null,
      "store_name": null,
      "rating": null,
      "review_count": null,
      "scraped_at": "2026-03-10T00:36:47.642340"
    },
    {
      "url": "https://www.tokopedia.com/nins-gadget/iphone-17-pro-256gb-paa-bnib-masih-segel-greenpeel-kualitas-terbaik-1733719989327529076",
      "name": "iPhone 17 Pro 256GB PAA BNIB Masih Segel Greenpeel Kualitas Terbaik",
      "price": "Rp24.800.000",
      "store_name": "Nin's Gadget",
      "rating": null,
      "review_count": null,
      "scraped_at": "2026-03-10T00:37:05.647055"
    },
    {
      "url": "https://www.tokopedia.com/jullindo-jis/apple-new-iphone-17-pro-17-pro-max-chip-a19-pro-256gb-512gb-1tb-2tb-garansi-resmi-1733388533953430818",
      "name": null,
      "price": null,
      "store_name": null,
      "rating": null,
      "review_count": null,
      "scraped_at": "2026-03-10T00:37:37.603437"
    },
    {
      "url": "https://www.tokopedia.com/imartmedan/iphone-17-pro-256gb-garansi-resmi-lengkap-bonus-warna-silver-orange-blue-1733246861609830165",
      "name": "iPhone 17 Pro 256GB Garansi Resmi Lengkap Bonus Warna Silver Orange Blue - BLUE",
      "price": "Rp24.747.000",
      "store_name": "IMART STORE",
      "rating": 5.0,
      "review_count": 1,
      "scraped_at": "2026-03-10T00:37:48.098878"
    },
    {
      "url": "https://www.tokopedia.com/mj18phone/iph-17-pro-256gb-512gb-1tb-garansi-resmi-indonesia-bnib-1733149607951107401",
      "name": null,
      "price": null,
      "store_name": null,
      "rating": null,
      "review_count": null,
      "scraped_at": "2026-03-10T00:38:27.565812"
    }
  ],
  "reviews": [
    {
      "review_id": "65f24403bf0f",
      "product_url": "https://www.tokopedia.com/kungfu-gadget/kg-apple-iphone-17-pro-series-garansi-resmi-ibox-gdn-1733195417491047609",
      "product_name": "(KG) Apple iPhone 17 Pro Series Garansi Resmi IBOX / GDN - Iphone 17 Pro 256GB, Deep Blue",
      "store_name": "Kungfu Gadget",
      "reviewer_name": "N***r",
      "rating": 5,
      "review_text": "Uhuuy sangat mantap, sangat puat. resmi segel BNIB. bakal langganan terus. respon admin juga gerceeep. Terimakasih",
      "review_date": "2 bulan lalu",
      "variant": "Varian: Iphone 17 Pro 512GB - Silver",
      "helpful_count": 0,
      "scraped_at": "2026-03-10T00:33:54.272199"
    },
    {
      "review_id": "63bdb1153611",
      "product_url": "https://www.tokopedia.com/kungfu-gadget/kg-apple-iphone-17-pro-series-garansi-resmi-ibox-gdn-1733195417491047609",
      "product_name": "(KG) Apple iPhone 17 Pro Series Garansi Resmi IBOX / GDN - Iphone 17 Pro 256GB, Deep Blue",
      "store_name": "Kungfu Gadget",
      "reviewer_name": "Anonymous",
      "rating": 5,
      "review_text": "selalu terbaik.. langganan pokoknya... puas beli disini",
      "review_date": "3 bulan lalu",
      "variant": "Varian: Iphone 17 Pro 256GB - Cosmic Orange",
      "helpful_count": 0,
      "scraped_at": "2026-03-10T00:33:54.835879"
    },
    {
      "review_id": "055ecc02807a",
      "product_url": "https://www.tokopedia.com/kungfu-gadget/kg-apple-iphone-17-pro-series-garansi-resmi-ibox-gdn-1733195417491047609",
      "product_name": "(KG) Apple iPhone 17 Pro Series Garansi Resmi IBOX / GDN - Iphone 17 Pro 256GB, Deep Blue",
      "store_name": "Kungfu Gadget",
      "reviewer_name": "I***s",
      "rating": 5,
      "review_text": "Admin sangat responsif, barangnya sampai dengan selamat allhamdulilah 🥰🙏🏻🤍",
      "review_date": "2 bulan lalu",
      "variant": "Varian: Iphone 17 Pro 256GB - Silver",
      "helpful_count": 0,
      "scraped_at": "2026-03-10T00:33:55.012949"
    },
    {
      "review_id": "7938631f1398",
      "product_url": "https://www.tokopedia.com/kungfu-gadget/kg-apple-iphone-17-pro-series-garansi-resmi-ibox-gdn-1733195417491047609",
      "product_name": "(KG) Apple iPhone 17 Pro Series Garansi Resmi IBOX / GDN - Iphone 17 Pro 256GB, Deep Blue",
      "store_name": "Kungfu Gadget",
      "reviewer_name": "Anonymous",
      "rating": 5,
      "review_text": "sesuai deskripsi mantaf Ty boskuh",
      "review_date": "2 minggu lalu",
      "variant": "Varian: Iphone 17 Pro 256GB - Silver",
      "helpful_count": 0,
      "scraped_at": "2026-03-10T00:33:55.256443"
    },
    {
      "review_id": "24bf699df079",
      "product_url": "https://www.tokopedia.com/kungfu-gadget/kg-apple-iphone-17-pro-series-garansi-resmi-ibox-gdn-1733195417491047609",
      "product_name": "(KG) Apple iPhone 17 Pro Series Garansi Resmi IBOX / GDN - Iphone 17 Pro 256GB, Deep Blue",
      "store_name": "Kungfu Gadget",
      "reviewer_name": "b***i",
      "rating": 5,
      "review_text": "Cepet banget",
      "review_date": "2 bulan lalu",
      "variant": "Varian: Iphone 17 Pro 256GB - Cosmic Orange",
      "helpful_count": 0,
      "scraped_at": "2026-03-10T00:33:55.401947"
    },
    {
      "review_id": "b6a112455455",
      "product_url": "https://www.tokopedia.com/kungfu-gadget/kg-apple-iphone-17-pro-series-garansi-resmi-ibox-gdn-1733195417491047609",
      "product_name": "(KG) Apple iPhone 17 Pro Series Garansi Resmi IBOX / GDN - Iphone 17 Pro 256GB, Deep Blue",
      "store_name": "Kungfu Gadget",
      "reviewer_name": "Anonymous",
      "rating": 5,
      "review_text": "sesuai iklan, mantap, sippp",
      "review_date": "1 bulan lalu",
      "variant": "Varian: Iphone 17 Pro 512GB - Deep Blue",
      "helpful_count": 0,
      "scraped_at": "2026-03-10T00:33:55.594923"
    },
    {
      "review_id": "e1d77769472b",
      "product_url": "https://www.tokopedia.com/kungfu-gadget/kg-apple-iphone-17-pro-series-garansi-resmi-ibox-gdn-1733195417491047609",
      "product_name": "(KG) Apple iPhone 17 Pro Series Garansi Resmi IBOX / GDN - Iphone 17 Pro 256GB, Deep Blue",
      "store_name": "Kungfu Gadget",
      "reviewer_name": "H***s",
      "rating": 5,
      "review_text": "Bener2 dah packing nya, salah satu official dengan packing yang sangat amat mantap",
      "review_date": "3 minggu lalu",
      "variant": "Varian: Iphone 17 Pro 256GB - Cosmic Orange",
      "helpful_count": 0,
      "scraped_at": "2026-03-10T00:33:55.731030"
    },
    {
      "review_id": "cce4548a4710",
      "product_url": "https://www.tokopedia.com/royalltech/apple-iphone-17-pro-1tb-all-collors-resmi-apple-indonesia-segel-greenpeel-1733546747226129911",
      "product_name": "APPLE iPhone 17 PRO 1TB All Collors Resmi APPLE INDONESIA Segel Greenpeel - COSMIC ORANGE, 256GB",
      "store_name": "royalltech",
      "reviewer_name": "G***x",
      "rating": 5,
      "review_text": "Barang sdh sampai diterima dalam kondisi baik, berfungsi baik. Seller responsif,, thankyou 🙏",
      "review_date": "2 bulan lalu",
      "variant": "Varian: DEEP BLUE - 256GB",
      "helpful_count": 0,
      "scraped_at": "2026-03-10T00:34:16.621176"
    },
    {
      "review_id": "7e6ab3f1c3e3",
      "product_url": "https://www.tokopedia.com/royalltech/apple-iphone-17-pro-1tb-all-collors-resmi-apple-indonesia-segel-greenpeel-1733546747226129911",
      "product_name": "APPLE iPhone 17 PRO 1TB All Collors Resmi APPLE INDONESIA Segel Greenpeel - COSMIC ORANGE, 256GB",
      "store_name": "royalltech",
      "reviewer_name": "A***i",
      "rating": 5,
      "review_text": "Diterima dengan baik Garansi ibox",
      "review_date": "2 bulan lalu",
      "variant": "Varian: DEEP BLUE - 256GB",
      "helpful_count": 0,
      "scraped_at": "2026-03-10T00:34:17.087557"
    },
    {
      "review_id": "ad4322d63ec5",
      "product_url": "https://www.tokopedia.com/royalltech/apple-iphone-17-pro-1tb-all-collors-resmi-apple-indonesia-segel-greenpeel-1733546747226129911",
      "product_name": "APPLE iPhone 17 PRO 1TB All Collors Resmi APPLE INDONESIA Segel Greenpeel - COSMIC ORANGE, 256GB",
      "store_name": "royalltech",
      "reviewer_name": "g***n",
      "rating": 5,
      "review_text": "mantap barang diterima dengan baikpengiriman cepat",
      "review_date": "9 bulan lalu",
      "variant": null,
      "helpful_count": 0,
      "scraped_at": "2026-03-10T00:34:17.937419"
    },
    {
      "review_id": "a3207afc6edc",
      "product_url": "https://www.tokopedia.com/royalltech/apple-iphone-17-pro-1tb-all-collors-resmi-apple-indonesia-segel-greenpeel-1733546747226129911",
      "product_name": "APPLE iPhone 17 PRO 1TB All Collors Resmi APPLE INDONESIA Segel Greenpeel - COSMIC ORANGE, 256GB",
      "store_name": "royalltech",
      "reviewer_name": "i***o",
      "rating": 5,
      "review_text": "produk mantapsfungsi semua normal tidak ada kendala",
      "review_date": "9 bulan lalu",
      "variant": null,
      "helpful_count": 0,
      "scraped_at": "2026-03-10T00:34:18.134708"
    },
    {
      "review_id": "d13cbcabcec4",
      "product_url": "https://www.tokopedia.com/royalltech/apple-iphone-17-pro-1tb-all-collors-resmi-apple-indonesia-segel-greenpeel-1733546747226129911",
      "product_name": "APPLE iPhone 17 PRO 1TB All Collors Resmi APPLE INDONESIA Segel Greenpeel - COSMIC ORANGE, 256GB",
      "store_name": "royalltech",
      "reviewer_name": "R***a",
      "rating": 5,
      "review_text": "pengiriman cepat, packing rapi dan kualitas bagus",
      "review_date": "8 bulan lalu",
      "variant": null,
      "helpful_count": 0,
      "scraped_at": "2026-03-10T00:34:18.298857"
    },
    {
      "review_id": "078e7e193dae",
      "product_url": "https://www.tokopedia.com/royalltech/apple-iphone-17-pro-1tb-all-collors-resmi-apple-indonesia-segel-greenpeel-1733546747226129911",
      "product_name": "APPLE iPhone 17 PRO 1TB All Collors Resmi APPLE INDONESIA Segel Greenpeel - COSMIC ORANGE, 256GB",
      "store_name": "royalltech",
      "reviewer_name": "i***o",
      "rating": 5,
      "review_text": "akhirnya barangnya sudah sampai dengan selamat",
      "review_date": "8 bulan lalu",
      "variant": null,
      "helpful_count": 0,
      "scraped_at": "2026-03-10T00:34:18.456438"
    },
    {
      "review_id": "33180ba6383e",
      "product_url": "https://www.tokopedia.com/royalltech/apple-iphone-17-pro-1tb-all-collors-resmi-apple-indonesia-segel-greenpeel-1733546747226129911",
      "product_name": "APPLE iPhone 17 PRO 1TB All Collors Resmi APPLE INDONESIA Segel Greenpeel - COSMIC ORANGE, 256GB",
      "store_name": "royalltech",
      "reviewer_name": "R***a",
      "rating": 5,
      "review_text": "Proses dan pengiriman cepat",
      "review_date": "8 bulan lalu",
      "variant": null,
      "helpful_count": 0,
      "scraped_at": "2026-03-10T00:34:18.622028"
    },
    {
      "review_id": "837e10b9b7fc",
      "product_url": "https://www.tokopedia.com/royalltech/apple-iphone-17-pro-1tb-all-collors-resmi-apple-indonesia-segel-greenpeel-1733546747226129911",
      "product_name": "APPLE iPhone 17 PRO 1TB All Collors Resmi APPLE INDONESIA Segel Greenpeel - COSMIC ORANGE, 256GB",
      "store_name": "royalltech",
      "reviewer_name": "Anonymous",
      "rating": 5,
      "review_text": "packing rapi kualitas bagus",
      "review_date": "8 bulan lalu",
      "variant": null,
      "helpful_count": 0,
      "scraped_at": "2026-03-10T00:34:18.819233"
    },
    {
      "review_id": "cd17c8e2d167",
      "product_url": "https://www.tokopedia.com/royalltech/apple-iphone-17-pro-1tb-all-collors-resmi-apple-indonesia-segel-greenpeel-1733546747226129911",
      "product_name": "APPLE iPhone 17 PRO 1TB All Collors Resmi APPLE INDONESIA Segel Greenpeel - COSMIC ORANGE, 256GB",
      "store_name": "royalltech",
      "reviewer_name": "i***o",
      "rating": 5,
      "review_text": "sesuai dengan keinginan",
      "review_date": "9 bulan lalu",
      "variant": null,
      "helpful_count": 0,
      "scraped_at": "2026-03-10T00:34:22.007349"
    },
    {
      "review_id": "a2572674ad68",
      "product_url": "https://www.tokopedia.com/royalltech/apple-iphone-17-pro-1tb-all-collors-resmi-apple-indonesia-segel-greenpeel-1733546747226129911",
      "product_name": "APPLE iPhone 17 PRO 1TB All Collors Resmi APPLE INDONESIA Segel Greenpeel - COSMIC ORANGE, 256GB",
      "store_name": "royalltech",
      "reviewer_name": "P***a",
      "rating": 5,
      "review_text": "berfungsi dengan baik",
      "review_date": "8 bulan lalu",
      "variant": null,
      "helpful_count": 0,
      "scraped_at": "2026-03-10T00:34:22.223257"
    },
    {
      "review_id": "907f91c3cbc0",
      "product_url": "https://www.tokopedia.com/royalltech/apple-iphone-17-pro-1tb-all-collors-resmi-apple-indonesia-segel-greenpeel-1733546747226129911",
      "product_name": "APPLE iPhone 17 PRO 1TB All Collors Resmi APPLE INDONESIA Segel Greenpeel - COSMIC ORANGE, 256GB",
      "store_name": "royalltech",
      "reviewer_name": "g***n",
      "rating": 5,
      "review_text": "barang original",
      "review_date": "9 bulan lalu",
      "variant": null,
      "helpful_count": 0,
      "scraped_at": "2026-03-10T00:34:22.321415"
    },
    {
      "review_id": "17d8b63f411b",
      "product_url": "https://www.tokopedia.com/royalltech/apple-iphone-17-pro-1tb-all-collors-resmi-apple-indonesia-segel-greenpeel-1733546747226129911",
      "product_name": "APPLE iPhone 17 PRO 1TB All Collors Resmi APPLE INDONESIA Segel Greenpeel - COSMIC ORANGE, 256GB",
      "store_name": "royalltech",
      "reviewer_name": "G***a",
      "rating": 5,
      "review_text": "okee bangettt",
      "review_date": "8 bulan lalu",
      "variant": null,
      "helpful_count": 0,
      "scraped_at": "2026-03-10T00:34:22.527807"
    },
    {
      "review_id": "8910fa820dd9",
      "product_url": "https://www.tokopedia.com/royalltech/apple-iphone-17-pro-1tb-all-collors-resmi-apple-indonesia-segel-greenpeel-1733546747226129911",
      "product_name": "APPLE iPhone 17 PRO 1TB All Collors Resmi APPLE INDONESIA Segel Greenpeel - COSMIC ORANGE, 256GB",
      "store_name": "royalltech",
      "reviewer_name": "g***n",
      "rating": 5,
      "review_text": "terima kasih",
      "review_date": "8 bulan lalu",
      "variant": null,
      "helpful_count": 0,
      "scraped_at": "2026-03-10T00:34:22.614693"
    },
    {
      "review_id": "783656159c11",
      "product_url": "https://www.tokopedia.com/royalltech/apple-iphone-17-pro-1tb-all-collors-resmi-apple-indonesia-segel-greenpeel-1733546747226129911",
      "product_name": "APPLE iPhone 17 PRO 1TB All Collors Resmi APPLE INDONESIA Segel Greenpeel - COSMIC ORANGE, 256GB",
      "store_name": "royalltech",
      "reviewer_name": "M***q",
      "rating": 5,
      "review_text": "Kejernihan lensa: top Kualitas pengerjaan: top Performa: top",
      "review_date": "2 bulan lalu",
      "variant": "Varian: DEEP BLUE - 256GB",
      "helpful_count": 0,
      "scraped_at": "2026-03-10T00:34:22.759562"
    },
    {
      "review_id": "fd446be54e18",
      "product_url": "https://www.tokopedia.com/royalltech/apple-iphone-17-pro-1tb-all-collors-resmi-apple-indonesia-segel-greenpeel-1733546747226129911",
      "product_name": "APPLE iPhone 17 PRO 1TB All Collors Resmi APPLE INDONESIA Segel Greenpeel - COSMIC ORANGE, 256GB",
      "store_name": "royalltech",
      "reviewer_name": "Anonymous",
      "rating": 5,
      "review_text": "Jangan khawatir ke asliannya 👌",
      "review_date": "1 bulan lalu",
      "variant": "Varian: SILVER - 256GB",
      "helpful_count": 0,
      "scraped_at": "2026-03-10T00:34:22.918439"
    },
    {
      "review_id": "0d01ea6b0eb4",
      "product_url": "https://www.tokopedia.com/agresponsel/iphone-17-pro-256gb-kamera-48mp-baterai-3998-mah-garansi-resmi-indonesia-1733361538893842199",
      "product_name": "iPhone 17 PRO 256GB Kamera 48MP & Baterai 3998 mAh Garansi Resmi Indonesia - DEEP BLUE",
      "store_name": "Unknown",
      "reviewer_name": "A***s",
      "rating": 5,
      "review_text": "barang ORI, thanks!",
      "review_date": "2 bulan lalu",
      "variant": "Varian: DEEP BLUE",
      "helpful_count": 0,
      "scraped_at": "2026-03-10T00:34:44.166452"
    },
    {
      "review_id": "23b40969df2a",
      "product_url": "https://www.tokopedia.com/ljsofficial/iphone-17-pro-256-gb-512-gb-1tb-garansi-resmi-indonesia-1732870514079991198",
      "product_name": "Iphone 17 Pro 256 GB 512 GB 1TB Garansi Resmi Indonesia - Blue, 256GB",
      "store_name": "LJS Phone",
      "reviewer_name": "Anonymous",
      "rating": 5,
      "review_text": "Barang sesuai unit segel garansi ****** aman.",
      "review_date": "4 bulan lalu",
      "variant": "Varian: Orange - 256GB",
      "helpful_count": 0,
      "scraped_at": "2026-03-10T00:35:01.305463"
    },
    {
      "review_id": "47ea7f7668c9",
      "product_url": "https://www.tokopedia.com/ljsofficial/iphone-17-pro-256-gb-512-gb-1tb-garansi-resmi-indonesia-1732870514079991198",
      "product_name": "Iphone 17 Pro 256 GB 512 GB 1TB Garansi Resmi Indonesia - Blue, 256GB",
      "store_name": "LJS Phone",
      "reviewer_name": "F***o",
      "rating": 5,
      "review_text": "terima kasih yah ka. paket sudah diterima dengan baik. seller amanah. sukses selalu yah seller",
      "review_date": "4 bulan lalu",
      "variant": "Varian: Orange - 256GB",
      "helpful_count": 0,
      "scraped_at": "2026-03-10T00:35:01.418052"
    },
    {
      "review_id": "89a8e45e99b4",
      "product_url": "https://www.tokopedia.com/r-shop-cahaya/iphone-17-pro-256gb-512gb-1tb-garansi-resmi-indonesia-ibox-paa-ida-saa-new-segel-original-garansi-1-tahun-1733155221240776623",
      "product_name": "Iphone 17 PRO 256GB/512GB/1TB Garansi (RESMI) Indonesia IBOX PAA IDA SAA NEW SEGEL ORIGINAL Garansi 1 Tahun - biru, 512GB",
      "store_name": "R Shop Cahaya",
      "reviewer_name": "Anonymous",
      "rating": 5,
      "review_text": "Mantap barang bagus pelayanan cepat",
      "review_date": "3 bulan lalu",
      "variant": "Varian: silver - 512GB",
      "helpful_count": 0,
      "scraped_at": "2026-03-10T00:36:18.121852"
    },
    {
      "review_id": "d4a34a3dae06",
      "product_url": "https://www.tokopedia.com/r-shop-cahaya/iphone-17-pro-256gb-512gb-1tb-garansi-resmi-indonesia-ibox-paa-ida-saa-new-segel-original-garansi-1-tahun-1733155221240776623",
      "product_name": "Iphone 17 PRO 256GB/512GB/1TB Garansi (RESMI) Indonesia IBOX PAA IDA SAA NEW SEGEL ORIGINAL Garansi 1 Tahun - biru, 512GB",
      "store_name": "R Shop Cahaya",
      "reviewer_name": "Anonymous",
      "rating": 5,
      "review_text": "Mantap Barang sesuai",
      "review_date": "2 bulan lalu",
      "variant": "Varian: biru - 256GB",
      "helpful_count": 0,
      "scraped_at": "2026-03-10T00:36:18.246967"
    },
    {
      "review_id": "3762a3fe49f2",
      "product_url": "https://www.tokopedia.com/r-shop-cahaya/iphone-17-pro-256gb-512gb-1tb-garansi-resmi-indonesia-ibox-paa-ida-saa-new-segel-original-garansi-1-tahun-1733155221240776623",
      "product_name": "Iphone 17 PRO 256GB/512GB/1TB Garansi (RESMI) Indonesia IBOX PAA IDA SAA NEW SEGEL ORIGINAL Garansi 1 Tahun - biru, 512GB",
      "store_name": "R Shop Cahaya",
      "reviewer_name": "Anonymous",
      "rating": 5,
      "review_text": "barang oriiiii",
      "review_date": "5 bulan lalu",
      "variant": "Varian: GreenTitanium - +BubelWrap",
      "helpful_count": 0,
      "scraped_at": "2026-03-10T00:36:18.370687"
    }
  ],
  "errors": []
}